clin_msi/count_normalization/__init__.py
clin_msi/count_normalization/normalize_counts.py
clin_msi/msi_model_scripts/__init__.py
clin_msi/msi_model_scripts/apply_msi_model.py
clin_msi/msi_model_scripts/msi_training.py
clin_msi/predict.py
clin_msi/train.py
clin_msi/utils.py
clin_msi-0.0.1.dist-info/WHEEL
clin_msi-0.0.1.dist-info/METADATA
clin_msi-0.0.1.dist-info/RECORD
